MANIFEST.in
README.rst
setup.py
gdrivefs/__init__.py
gdrivefs/account_info.py
gdrivefs/auto_auth.py
gdrivefs/buffer_segments.py
gdrivefs/cache_agent.py
gdrivefs/cache_registry.py
gdrivefs/cacheclient_base.py
gdrivefs/change.py
gdrivefs/chunked_download.py
gdrivefs/conf.py
gdrivefs/constants.py
gdrivefs/displaced_file.py
gdrivefs/drive.py
gdrivefs/errors.py
gdrivefs/fsutility.py
gdrivefs/gdfuse.py
gdrivefs/livereader_base.py
gdrivefs/normal_entry.py
gdrivefs/oauth_authorize.py
gdrivefs/opened_file.py
gdrivefs/state.py
gdrivefs/time_support.py
gdrivefs/utility.py
gdrivefs/volume.py
gdrivefs.egg-info/PKG-INFO
gdrivefs.egg-info/SOURCES.txt
gdrivefs.egg-info/dependency_links.txt
gdrivefs.egg-info/not-zip-safe
gdrivefs.egg-info/requires.txt
gdrivefs.egg-info/top_level.txt
gdrivefs/config/__init__.py
gdrivefs/config/changes.py
gdrivefs/config/fs.py
gdrivefs/config/log.py
gdrivefs/resources/README.rst
gdrivefs/resources/requirements.txt
gdrivefs/resources/requirements_freeze.txt
gdrivefs/resources/scripts/gdfs
gdrivefs/resources/scripts/gdfsdumpentry
gdrivefs/resources/scripts/gdfstool