Metadata-Version: 2.1
Name: gdrivefs
Version: 0.14.12
Summary: A complete FUSE adapter for Google Drive.
Home-page: https://github.com/dsoprea/GDriveFS
Author: Dustin Oprea
Author-email: myselfasunder@gmail.com
License: GPL 2
Keywords: google-drive google drive fuse filesystem
Platform: UNKNOWN
Classifier: Topic :: System :: Filesystems
Classifier: Development Status :: 4 - Beta
Classifier: Environment :: Console
Classifier: Intended Audience :: End Users/Desktop
Classifier: Intended Audience :: System Administrators
Classifier: License :: OSI Approved :: BSD License
Classifier: Natural Language :: English
Classifier: Operating System :: POSIX
Classifier: Programming Language :: Python
Classifier: Topic :: Internet
Classifier: Topic :: Utilities
